zentool/__init__.py
zentool/version.py
zentool/lib/__init__.py
zentool/lib/combo.py
zentool/lib/google_sheet.py
zentool/lib/sheet_range.py
zentool/lib/zenhub.py
zentool/tools/__init__.py
zentool/tools/commentator.py
zentool/tools/issue_creator.py
zentool/tools/make_spreadsheet.py
zentool/tools/release_assigner.py
zentool/tools/repo_map.py
zentool/tools/spreadsheet_processor.py
zentool/tools/spreadsheet_tools.py
zentool/tools/sync_spreadsheet.py
zentool-1.1.1.data/scripts/zentool
zentool-1.1.1.dist-info/LICENSE
zentool-1.1.1.dist-info/METADATA
zentool-1.1.1.dist-info/WHEEL
zentool-1.1.1.dist-info/top_level.txt
zentool-1.1.1.dist-info/RECORD
