Metadata-Version: 2.1
Name: zentool
Version: 1.1.1
Summary: Tool for manipulating ZenHub / GitHub using Google Sheets
Home-page: https://github.com/HumanCellAtlas/zentool
Author: Sam Pierson
Author-email: spierson@chanzuckerberg.com
License: MIT
Platform: MacOS X
Platform: Posix
Classifier: Intended Audience :: Developers
Classifier: License :: OSI Approved :: MIT License
Classifier: Operating System :: MacOS :: MacOS X
Classifier: Operating System :: POSIX
Classifier: Programming Language :: Python :: 3.6
Requires-Dist: PyGithub
Requires-Dist: google-api-python-client
Requires-Dist: google-auth-oauthlib
Requires-Dist: google-auth-httplib2
Requires-Dist: requests
Requires-Dist: colored
